pyonwater/__init__.py
pyonwater/account.py
pyonwater/client.py
pyonwater/exceptions.py
pyonwater/meter.py
pyonwater/meter_reader.py
pyonwater/models/__init__.py
pyonwater/models/eow_historical_models.py
pyonwater/models/eow_models.py
pyonwater/models/models.py
pyonwater/models/units.py
pyonwater/units.py
pyonwater-0.3.15.dist-info/LICENSE
pyonwater-0.3.15.dist-info/METADATA
pyonwater-0.3.15.dist-info/WHEEL
pyonwater-0.3.15.dist-info/RECORD
